{
  "generated_at": "2026-07-15T20:40:55Z",
  "tier_timestamps": {
    "fast": "2026-07-15T20:40:55Z",
    "bills": "2026-07-15T19:42:38Z"
  },
  "counts_by_source": {
    "gdelt": 686,
    "rss-dcd": 130,
    "rss-rto-insider": 22,
    "rss-dck": 22,
    "rss-arstechnica": 9,
    "rss-latitude": 6,
    "rss-canary": 4,
    "rss-utilitydive": 12,
    "rss-court-dc": 1,
    "reddit": 59,
    "tiktok": 9,
    "x": 6,
    "instagram": 3,
    "youtube": 1,
    "polymarket": 2,
    "news": 3
  },
  "run_stats": {
    "last_run_seconds": 25.67,
    "raw_fetched": {
      "youtube": 0,
      "rss": 190,
      "reddit": 0,
      "gdelt": 0
    },
    "inserted": 0,
    "updated": 14,
    "dropped_irrelevant": 176,
    "accepted_by_source_this_run": {
      "rss-dcd": 2,
      "rss-arstechnica": 1,
      "rss-canary": 1,
      "rss-latitude": 1,
      "rss-rto-insider": 1,
      "rss-dck": 7,
      "rss-court-dc": 1
    }
  }
}