{
  "generated_at": "2026-04-23T22:07:09Z",
  "tier_timestamps": {
    "fast": "2026-04-23T22:07:09Z"
  },
  "counts_by_source": {
    "reddit": 50,
    "tiktok": 8,
    "rss-utilitydive": 2,
    "rss-dcd": 3,
    "instagram": 6,
    "x": 14,
    "youtube": 2,
    "gdelt": 5,
    "polymarket": 2,
    "news": 11,
    "rss-dck": 3,
    "legal": 1
  },
  "run_stats": {
    "last_run_seconds": 37.29,
    "raw_fetched": {
      "youtube": 0,
      "rss": 190,
      "reddit": 0,
      "gdelt": 10
    },
    "inserted": 0,
    "updated": 8,
    "dropped_irrelevant": 192,
    "accepted_by_source_this_run": {
      "rss-dcd": 3,
      "rss-utilitydive": 2,
      "rss-dck": 3
    }
  }
}