{
  "generated_at": "2026-04-28T14:49:12Z",
  "tier_timestamps": {
    "fast": "2026-04-28T13:05:02Z",
    "bills": "2026-04-28T14:49:12Z"
  },
  "counts_by_source": {
    "gdelt": 36,
    "rss-canary": 1,
    "rss-dck": 4,
    "rss-utilitydive": 4,
    "rss-dcd": 8,
    "reddit": 66,
    "tiktok": 15,
    "x": 19,
    "instagram": 7,
    "youtube": 2,
    "polymarket": 2,
    "news": 11,
    "legal": 1
  },
  "run_stats": {
    "last_run_seconds": 31.64,
    "raw_fetched": {
      "youtube": 0,
      "rss": 190,
      "reddit": 0,
      "gdelt": 6
    },
    "inserted": 1,
    "updated": 7,
    "dropped_irrelevant": 188,
    "accepted_by_source_this_run": {
      "rss-utilitydive": 2,
      "rss-canary": 1,
      "rss-dck": 4,
      "gdelt": 1
    },
    "bills_last_run_seconds": 583.47,
    "bills_raw_fetched": 0,
    "bills_inserted": 0,
    "bills_updated": 0,
    "bills_noop": 0,
    "bills_total_in_json": 193,
    "bills_states_with_bills": 16
  }
}