{
  "generated_at": "2026-06-24T01:21:35Z",
  "tier_timestamps": {
    "fast": "2026-06-24T01:21:35Z",
    "bills": "2026-06-24T00:13:04Z"
  },
  "counts_by_source": {
    "rss-rto-insider": 16,
    "gdelt": 532,
    "rss-dcd": 81,
    "rss-latitude": 4,
    "rss-utilitydive": 12,
    "rss-canary": 3,
    "rss-arstechnica": 8,
    "rss-dck": 16,
    "rss-court-dc": 1,
    "reddit": 64,
    "tiktok": 15,
    "x": 18,
    "instagram": 7,
    "youtube": 2,
    "polymarket": 2,
    "news": 10,
    "legal": 1
  },
  "run_stats": {
    "last_run_seconds": 22.72,
    "raw_fetched": {
      "youtube": 0,
      "rss": 190,
      "reddit": 0,
      "gdelt": 46
    },
    "inserted": 5,
    "updated": 7,
    "dropped_irrelevant": 222,
    "accepted_by_source_this_run": {
      "rss-dcd": 1,
      "rss-latitude": 1,
      "rss-canary": 1,
      "rss-dck": 3,
      "rss-rto-insider": 1,
      "rss-court-dc": 1,
      "gdelt": 4
    }
  }
}